Kalkoltorsmdm/__init__.py
Kalkoltorsmdm-0.1.dist-info/LICENCE.txt
Kalkoltorsmdm-0.1.dist-info/METADATA
Kalkoltorsmdm-0.1.dist-info/WHEEL
Kalkoltorsmdm-0.1.dist-info/top_level.txt
Kalkoltorsmdm-0.1.dist-info/RECORD
